fastqc_db/__init__.py
fastqc_db/__main__.py
fastqc_db/fastqc_db.py
fastqc_db/main.py
fastqc_db-0.22.dist-info/DESCRIPTION.rst
fastqc_db-0.22.dist-info/METADATA
fastqc_db-0.22.dist-info/RECORD
fastqc_db-0.22.dist-info/WHEEL
fastqc_db-0.22.dist-info/metadata.json
fastqc_db-0.22.dist-info/top_level.txt
fastqc_sqlite/__init__.py
fastqc_sqlite/__main__.py
fastqc_sqlite/fastqc_db.py
fastqc_sqlite/main.py
